README.md
setup.cfg
setup.py
metrdsutil/__init__.py
metrdsutil.egg-info/PKG-INFO
metrdsutil.egg-info/SOURCES.txt
metrdsutil.egg-info/dependency_links.txt
metrdsutil.egg-info/requires.txt
metrdsutil.egg-info/top_level.txt
metrdsutil/db/__init__.py
metrdsutil/db/db.py
metrdsutil/jupyter/__init__.py
metrdsutil/jupyter/jupyter.py
metrdsutil/plot/__init__.py
metrdsutil/plot/plot.py